superhooks/__init__.py
superhooks/superhooks.py
superhooks/tests/__init__.py
superhooks/tests/superhooks_test.py
superhooks-0.6.dist-info/METADATA
superhooks-0.6.dist-info/RECORD
superhooks-0.6.dist-info/WHEEL
superhooks-0.6.dist-info/entry_points.txt
superhooks-0.6.dist-info/top_level.txt
