Metadata-Version: 2.1
Name: superhooks
Version: 0.6
Summary: superhooks plugin for supervisord
Home-page: https://github.com/skyrocknroll/superhooks
Author: Yuvaraj Loganathan
Author-email: uvaraj6@gmail.com
Maintainer: Yuvaraj Loganathan
Maintainer-email: uvaraj6@gmail.com
License: BSD-derived (http://www.repoze.org/LICENSE.txt)
Keywords: supervisor web hooks monitoring
Platform: UNKNOWN
Classifier: Development Status :: 3 - Alpha
Classifier: Environment :: No Input/Output (Daemon)
Classifier: Intended Audience :: System Administrators
Classifier: Natural Language :: English
Classifier: Operating System :: POSIX
Classifier: Programming Language :: Python :: 2
Classifier: Programming Language :: Python :: 2.6
Classifier: Programming Language :: Python :: 2.7
Classifier: Programming Language :: Python :: 3
Classifier: Programming Language :: Python :: 3.2
Classifier: Programming Language :: Python :: 3.3
Classifier: Programming Language :: Python :: 3.4
Classifier: Programming Language :: Python :: 3.5
Classifier: Programming Language :: Python :: 3.6
Classifier: Programming Language :: Python :: 3.7
Classifier: Topic :: System :: Boot
Classifier: Topic :: System :: Monitoring
Classifier: Topic :: System :: Systems Administration
Requires-Dist: superlance
Requires-Dist: supervisor
Requires-Dist: requests
